crowdstrike_aidr_openai/__init__.py
crowdstrike_aidr_openai/_client.py
crowdstrike_aidr_openai/_exceptions.py
crowdstrike_aidr_openai/_resource.py
crowdstrike_aidr_openai/lib/__init__.py
crowdstrike_aidr_openai/lib/azure.py
crowdstrike_aidr_openai/py.typed
crowdstrike_aidr_openai/resources/responses/__init__.py
crowdstrike_aidr_openai/resources/responses/responses.py
crowdstrike_aidr_openai-0.1.0.dist-info/WHEEL
crowdstrike_aidr_openai-0.1.0.dist-info/METADATA
crowdstrike_aidr_openai-0.1.0.dist-info/RECORD
