Metadata-Version: 2.4
Name: crowdstrike-aidr-openai
Version: 0.1.0
Summary: A wrapper around the OpenAI Python library that wraps the Responses API with CrowdStrike AIDR
Author: CrowdStrike
Author-email: CrowdStrike <support@crowdstrike.com>
License-Expression: MIT
Requires-Dist: anyio~=4.12.0
Requires-Dist: crowdstrike-aidr~=0.3.0
Requires-Dist: httpx~=0.28.1
Requires-Dist: openai~=2.8.1
Requires-Dist: pydantic-core~=2.41.5
Requires-Dist: typing-extensions~=4.15.0
Requires-Python: >=3.12
